{
        "LAT": [
            {"value":"/", "occurrence": "1"},
        {"value":"cogitatis", "occurrence": "1"},
        {"value":"fidei", "occurrence": "1"},
        {"value":"inter", "occurrence": "1"},
        {"value":"modicae", "occurrence": "1"},
        {"value":"quid", "occurrence": "1"},
        {"value":"uos", "occurrence": "1"}
        ],
                        "pos": [
            {"value":"A", "occurrence": "1"},
        {"value":"N", "occurrence": "1"},
        {"value":"P", "occurrence": "1"},
        {"value":"PRONINTERR", "occurrence": "1"},
        {"value":"PRONPRS", "occurrence": "2"},
        {"value":"V", "occurrence": "1"}
        ]
                        
        }
    