<?xml version="1.0" ?><sDocumentInfo generatedOn="2015-06-01 17:18:03" sName="T_070__30_beta" id="salt:/b4.tatian/T_070__30_beta"><metaDataInfo><entry key="page">070</entry><entry key="X::abbreviation">X</entry><entry key="corpus-code">T</entry><entry key="line">30</entry><entry key="writer">beta</entry><entry key="X::sex">m</entry></metaDataInfo><structuralInfo><entry key="SNode">80</entry><entry key="STimeline">1</entry><entry key="STextualDS">1</entry><entry key="SToken">16</entry><entry key="SSpan">62</entry><entry key="SRelation">184</entry><entry key="SSpanningRelation">152</entry></structuralInfo><sAnnotationInfo sName="foc-bg" occurrence="3"><sValue occurrence="1">CF_02</sValue><sValue occurrence="1">CF_01</sValue><sValue occurrence="1">NIF</sValue></sAnnotationInfo><sAnnotationInfo sName="syl_no" occurrence="8"><sValue occurrence="1">4</sValue><sValue occurrence="2">3</sValue><sValue occurrence="1">2</sValue><sValue occurrence="1">10</sValue><sValue occurrence="3">1</sValue></sAnnotationInfo><sAnnotationInfo sName="LAT" occurrence="14"><sValue occurrence="1">sua</sValue><sValue occurrence="1">quoniam</sValue><sValue occurrence="1">gloria</sValue><sValue occurrence="1">sicut</sValue><sValue occurrence="1">nec</sValue><sValue occurrence="1">istis</sValue><sValue occurrence="1">coopertus</sValue><sValue occurrence="1">ex</sValue><sValue occurrence="1">in</sValue><sValue occurrence="1">est</sValue><sValue occurrence="1">omni</sValue><sValue occurrence="1">unum</sValue><sValue occurrence="1">/</sValue><sValue occurrence="1">salomon</sValue></sAnnotationInfo><sAnnotationInfo sName="givenness" occurrence="2"><sValue occurrence="1">ACC</sValue><sValue occurrence="1">GIV</sValue></sAnnotationInfo><sAnnotationInfo sName="bibl" occurrence="1"><sValue occurrence="1">T 70, 30 Beta Mt 6</sValue></sAnnotationInfo><sAnnotationInfo sName="top-comm" occurrence="2"><sValue occurrence="1">TOP</sValue><sValue occurrence="1">COMM</sValue></sAnnotationInfo><sAnnotationInfo sName="comment" occurrence="1"><sValue occurrence="1">Voranstellung des Vfin; Kontrastfokus (selbst Salomon, und zwar bei all seinem Ruhm);  Part als PrädN in einer Kopuilativkonstruktion</sValue></sAnnotationInfo><sAnnotationInfo sName="clause-status" occurrence="1"><sValue occurrence="1">SUB</sValue></sAnnotationInfo><sAnnotationInfo sName="align" occurrence="3"><sValue occurrence="1">=L11</sValue><sValue occurrence="1">=L1</sValue><sValue occurrence="1">=L9</sValue></sAnnotationInfo><sAnnotationInfo sName="aboutness" occurrence="1"><sValue occurrence="1">AB</sValue></sAnnotationInfo><sAnnotationInfo sName="pos" occurrence="13"><sValue occurrence="1">VAUX</sValue><sValue occurrence="1">CONJ</sValue><sValue occurrence="3">P</sValue><sValue occurrence="1">PRONINDEF</sValue><sValue occurrence="2">N</sValue><sValue occurrence="1">PRONPOS</sValue><sValue occurrence="1">VN</sValue><sValue occurrence="2">ADV</sValue><sValue occurrence="1">PRONDEM</sValue></sAnnotationInfo><sAnnotationInfo sName="gf" occurrence="5"><sValue occurrence="1">VFIN</sValue><sValue occurrence="1">PARTPF</sValue><sValue occurrence="1">SUBJ</sValue><sValue occurrence="2">ADVMOD</sValue></sAnnotationInfo><sAnnotationInfo sName="cat" occurrence="5"><sValue occurrence="1">PP</sValue><sValue occurrence="2">VP</sValue><sValue occurrence="2">NP</sValue></sAnnotationInfo><sAnnotationInfo sName="definiteness" occurrence="3"><sValue occurrence="3">DEF</sValue></sAnnotationInfo></sDocumentInfo>