<?xml version="1.0" ?><sDocumentInfo generatedOn="2015-06-01 17:18:21" sName="T_132__13_gamma" id="salt:/b4.tatian/T_132__13_gamma"><metaDataInfo><entry key="page">132</entry><entry key="X::abbreviation">X</entry><entry key="corpus-code">T</entry><entry key="line">13</entry><entry key="writer">gamma</entry><entry key="X::sex">m</entry></metaDataInfo><structuralInfo><entry key="SNode">25</entry><entry key="STimeline">1</entry><entry key="STextualDS">1</entry><entry key="SToken">5</entry><entry key="SSpan">18</entry><entry key="SRelation">43</entry><entry key="SSpanningRelation">33</entry></structuralInfo><sAnnotationInfo sName="syl_no" occurrence="3"><sValue occurrence="1">4</sValue><sValue occurrence="1">3</sValue><sValue occurrence="1">1</sValue></sAnnotationInfo><sAnnotationInfo sName="LAT" occurrence="3"><sValue occurrence="1">oport&amp;</sValue><sValue occurrence="1">adorare</sValue><sValue occurrence="1">ubi</sValue></sAnnotationInfo><sAnnotationInfo sName="bibl" occurrence="1"><sValue occurrence="1">T 132, 13 Gamma Io 4, 20</sValue></sAnnotationInfo><sAnnotationInfo sName="comment" occurrence="1"><sValue occurrence="1">wohl V2 im NS nach Umstellung; Satzstatus allerdings unklar; ohne Subjekt</sValue></sAnnotationInfo><sAnnotationInfo sName="clause-status" occurrence="1"><sValue occurrence="1">SUBLOC</sValue></sAnnotationInfo><sAnnotationInfo sName="align" occurrence="1"><sValue occurrence="1">=L4</sValue></sAnnotationInfo><sAnnotationInfo sName="pos" occurrence="4"><sValue occurrence="2">V</sValue><sValue occurrence="1">P</sValue><sValue occurrence="1">ADV</sValue></sAnnotationInfo><sAnnotationInfo sName="gf" occurrence="3"><sValue occurrence="1">INF</sValue><sValue occurrence="1">VFIN</sValue><sValue occurrence="1">ADVLOC</sValue></sAnnotationInfo><sAnnotationInfo sName="cat" occurrence="1"><sValue occurrence="1">VP</sValue></sAnnotationInfo></sDocumentInfo>